unimath/__init__.py
unimath/calculus.py
unimath/combinatorics.py
unimath/errors.py
unimath/matrix.py
unimath/mset.py
unimath/parse.py
unimath/plane_geometry.py
unimath/range.py
unimath/sets.py
unimath/symbolic.py
unimath/core/__init__.py
unimath/definitions/__init__.py
unimath/definitions/test.py
unimath-1.4.3.dist-info/licenses/LICENSE
unimath-1.4.3.dist-info/METADATA
unimath-1.4.3.dist-info/WHEEL
unimath-1.4.3.dist-info/top_level.txt
unimath-1.4.3.dist-info/RECORD
