Metadata-Version: 2.4
Name: unimath
Version: 1.4.3
Summary: Mathematical Environment Library in Python
Home-page: https://github.com/Jolankaa/unimath
Author: Poyraz Soylu
Author-email: psoylu3467@gmail.com
Classifier: Programming Language :: Python :: 3
Classifier: License :: OSI Approved :: MIT License
Classifier: Operating System :: OS Independent
Requires-Python: >=3.8
License-File: LICENSE
Requires-Dist: sympy
Requires-Dist: matplotlib
Dynamic: author
Dynamic: author-email
Dynamic: classifier
Dynamic: description
Dynamic: description-content-type
Dynamic: home-page
Dynamic: license-file
Dynamic: requires-dist
Dynamic: requires-python
Dynamic: summary
